calfi/__init__.py
calfi/conventions.py
calfi/fin_cal.py
calfi/py.typed
calfi-1.0.0.dist-info/METADATA
calfi-1.0.0.dist-info/WHEEL
calfi-1.0.0.dist-info/RECORD
