Metadata-Version: 2.4
Name: calfi
Version: 1.0.0
Summary: A Python library for financial date calculations, business calendars, and day count conventions
Requires-Python: >=3.13
